{
    "id": 7642,
    "question": "Gewinnt Lara Gut-Behrami den Gesamtweltcup?",
    "created_at": "2021-02-27T13:49:41+00:00",
    "updated_at": "2021-06-14T09:38:56+00:00",
    "end_at": null,
    "comment_group_id": 2040821,
    "published_at": "2021-03-07T12:31:28+00:00",
    "display_name": "",
    "total": 1040,
    "answers": [
        {
            "id": 17611,
            "answer": "Ja, in ihrer Überform muss das reichen.",
            "votes": 653,
            "order": 0
        },
        {
            "id": 17610,
            "answer": "Nein, das klappt leider nicht.",
            "votes": 387,
            "order": 1
        }
    ]
}