{
    "id": 2432,
    "question": "Finden Sie die ESAF-Regelung sexistisch?",
    "created_at": "2019-08-27T06:56:39+00:00",
    "updated_at": "2021-06-14T10:21:16+00:00",
    "end_at": null,
    "comment_group_id": null,
    "published_at": null,
    "display_name": "",
    "total": 240,
    "answers": [
        {
            "id": 6119,
            "answer": "Ja, wir schreiben doch das Jahr 2019.",
            "votes": 131,
            "order": 0
        },
        {
            "id": 6120,
            "answer": "Nein, wo ist das Problem?",
            "votes": 109,
            "order": 1
        }
    ]
}